{"name":"build-javascript","namedChunkGroups":{"polyfill":{"name":"polyfill","assets":[{"name":"webpack-runtime-159643ec0132dd5d86ca.js","size":3260},{"name":"polyfill-8ddaef51e6a3dee3a8b0.js","size":85864}],"filteredAssets":0,"assetsSize":89124,"filteredAuxiliaryAssets":2,"auxiliaryAssetsSize":221402},"app":{"name":"app","assets":[{"name":"webpack-runtime-159643ec0132dd5d86ca.js","size":3260},{"name":"framework-31ef7bb24b14d9df055b.js","size":128736},{"name":"app-78660ca29235c967dc6f.js","size":52191}],"filteredAssets":0,"assetsSize":184187,"filteredAuxiliaryAssets":3,"auxiliaryAssetsSize":547061},"component---src-pages-404-js":{"name":"component---src-pages-404-js","assets":[{"name":"component---src-pages-404-js-55c5c494299e9a4780cc.js","size":16814}],"filteredAssets":0,"assetsSize":16814,"filteredAuxiliaryAssets":1,"auxiliaryAssetsSize":69397},"component---src-pages-index-tsx":{"name":"component---src-pages-index-tsx","assets":[{"name":"component---src-pages-index-tsx-4f906547efeece2526c3.js","size":90304}],"filteredAssets":0,"assetsSize":90304,"filteredAuxiliaryAssets":1,"auxiliaryAssetsSize":287969}},"assetsByChunkName":{"polyfill":["webpack-runtime-159643ec0132dd5d86ca.js","polyfill-8ddaef51e6a3dee3a8b0.js"],"app":["webpack-runtime-159643ec0132dd5d86ca.js","framework-31ef7bb24b14d9df055b.js","app-78660ca29235c967dc6f.js"],"component---src-pages-404-js":["component---src-pages-404-js-55c5c494299e9a4780cc.js"],"component---src-pages-index-tsx":["component---src-pages-index-tsx-4f906547efeece2526c3.js"]},"childAssetsByChunkName":{}}